mobilemoney/__init__.py
mobilemoney/client.py
mobilemoney/errors/__init__.py
mobilemoney/errors/errors.py
mobilemoney/request/__init__.py
mobilemoney/request/collection.py
mobilemoney/request/disbursements.py
mobilemoney/request/http.py
mobilemoney/request/request.py
mobilemoney/request/route.py
mobilemoney/utils/__init__.py
mobilemoney/utils/utils.py
mobilemoney.py-0.1.2.dist-info/LICENSE
mobilemoney.py-0.1.2.dist-info/METADATA
mobilemoney.py-0.1.2.dist-info/WHEEL
mobilemoney.py-0.1.2.dist-info/top_level.txt
mobilemoney.py-0.1.2.dist-info/RECORD
