Metadata-Version: 2.1
Name: mobilemoney.py
Version: 0.1.2
Summary: A Python wrapper for the MoMo Open API
Home-page: https://rewriteapi.cm/momo
Author: rewriteapi
Author-email: <support@rewriteapi.cm>
License: MIT
Project-URL: Documentation, https://momopy.rewriteapi.cm
Project-URL: Website, https://rewriteapi.cm
Project-URL: Repository, https://github.com/rewriteapi/mobilemoney.py
Keywords: python,mobilemoney,MTN Money,rewriteapi,MTN API,mobilemoney-py
Platform: UNKNOWN
Classifier: Development Status :: 5 - Production/Stable
Classifier: License :: OSI Approved :: MIT License
Classifier: Intended Audience :: Developers
Classifier: Natural Language :: English
Classifier: Operating System :: OS Independent
Classifier: Programming Language :: Python :: 3.8
Classifier: Programming Language :: Python :: 3.9
Classifier: Programming Language :: Python :: 3.10
Classifier: Topic :: Internet
Classifier: Topic :: Software Development :: Libraries
Classifier: Topic :: Software Development :: Libraries :: Python Modules
Classifier: Topic :: Utilities
Classifier: Typing :: Typed
Requires-Python: >=3.8.0
License-File: LICENSE
Requires-Dist: aiohttp (<4,>=3.7.4)
